hpcwizard/__init__.py
hpcwizard/cmdline.py
hpcwizard/common.py
hpcwizard/err.py
hpcwizard/logger.py
hpcwizard/main.py
hpcwizard/subcmd_gen_workflow.py
hpcwizard/workflow.py
hpcwizard-0.1.0.dist-info/LICENSE
hpcwizard-0.1.0.dist-info/METADATA
hpcwizard-0.1.0.dist-info/WHEEL
hpcwizard-0.1.0.dist-info/entry_points.txt
hpcwizard-0.1.0.dist-info/RECORD
