Metadata-Version: 2.3
Name: hpcwizard
Version: 0.1.0
Summary: Python workflow framework
License: CeCILL
Keywords: hpc,workflow
Author: Maxime BLANCHON
Author-email: maxime.blanchon@cnrgh.fr
Requires-Python: >=3.11
Classifier: Development Status :: 3 - Alpha
Classifier: Intended Audience :: Developers
Classifier: License :: CeCILL-C Free Software License Agreement (CECILL-C)
Classifier: Programming Language :: Python :: 3.8
Requires-Dist: colorlog (==6.7.0)
Requires-Dist: networkx (>=3.5,<4.0)
Requires-Dist: pyyaml (>=6.0.2,<7.0.0)
Requires-Dist: rich-argparse (>=1.7.1,<2.0.0)
Requires-Dist: schema (>=0.7.7,<0.8.0)
